{
  "songs": [
    {
      "id": 1,
      "name": "Southbound",
      "artist": "Carrie Underwood",
      "songUrl": "https://open.spotify.com/embed/track/7qXPZxXn6Xmv1sjh03skiW",
      "year": "2018",
      "likes": 1
    },
    {
      "id": 2,
      "name": "Peaches",
      "artist": "Justin Bieber",
      "songUrl": "https://open.spotify.com/embed/track/4iJyoBOLtHqaGxP12qzhQI",
      "year": "2021",
      "likes": 0
    },
    {
      "id": 3,
      "name": "Summer",
      "artist": "Calvin Harris",
      "songUrl": "https://open.spotify.com/embed/track/6YUTL4dYpB9xZO5qExPf05",
      "year": "2014",
      "likes": 0
    },
    {
      "id": 4,
      "name": "Cake By The Ocean",
      "artist": "DNCE",
      "songUrl": "https://open.spotify.com/embed/track/76hfruVvmfQbw0eYn1nmeC",
      "year": "2016",
      "likes": 3
    },
    {
      "id": 5,
      "name": "Treasure",
      "artist": "Bruno Mars",
      "songUrl": "https://open.spotify.com/embed/track/55h7vJchibLdUkxdlX3fK7",
      "year": "2012",
      "likes": 2
    },
    {
      "id": 6,
      "name": "Beach Cowboy",
      "artist": "Brian Kelley",
      "songUrl": "https://open.spotify.com/embed/track/0hYyHSuIKAvSdv1MwUkojC",
      "year": "2021",
      "likes": 0
    },
    {
      "id": 7,
      "name": "Better on the Water",
      "artist": "Ashley McBryde",
      "songUrl": "https://open.spotify.com/embed/track/1eKE1jKNvEHm4BreOJofs6",
      "year": "2016",
      "likes": 2
    }
  ]
}